.gitignore
CHANGES.rst
MANIFEST.in
README.rst
setup.py
docs/INSTALL.txt
docs/LICENSE.GPL
docs/LICENSE.txt
plone/__init__.py
plone.directives.form.egg-info/PKG-INFO
plone.directives.form.egg-info/SOURCES.txt
plone.directives.form.egg-info/dependency_links.txt
plone.directives.form.egg-info/entry_points.txt
plone.directives.form.egg-info/namespace_packages.txt
plone.directives.form.egg-info/not-zip-safe
plone.directives.form.egg-info/requires.txt
plone.directives.form.egg-info/top_level.txt
plone/directives/__init__.py
plone/directives/form/__init__.py
plone/directives/form/configure.zcml
plone/directives/form/error.py
plone/directives/form/form.py
plone/directives/form/meta.py
plone/directives/form/meta.zcml
plone/directives/form/schema.py
plone/directives/form/validator.py
plone/directives/form/value.py
plone/directives/form/tests/__init__.py
plone/directives/form/tests/schema.txt
plone/directives/form/tests/test_error.py
plone/directives/form/tests/test_form.py
plone/directives/form/tests/test_schema.py
plone/directives/form/tests/test_validator.py
plone/directives/form/tests/test_value.py
plone/directives/form/tests/test_form_templates/testformwithtemplate.pt