Metadata-Version: 1.1
Name: plone.directives.form
Version: 2.0.1
Summary: Grok-like directives configuring forms
Home-page: http://code.google.com/p/dexterity
Author: Martin Aspeli
Author-email: optilude@gmail.com
License: GPL
Keywords: grok plone dexterity form content
Platform: UNKNOWN
Classifier: Framework :: Plone
Classifier: Programming Language :: Python
Classifier: Topic :: Software Development :: Libraries :: Python Modules
